game_theory_optimal_poker/__init__.py
game_theory_optimal_poker/__main__.py
game_theory_optimal_poker/auth.py
game_theory_optimal_poker/db.py
game_theory_optimal_poker/play.py
game_theory_optimal_poker/poker.py
game_theory_optimal_poker/poker_cli.py
game_theory_optimal_poker/schema.sql
game_theory_optimal_poker/static/dealer.png
game_theory_optimal_poker/static/style.css
game_theory_optimal_poker/templates/base.html
game_theory_optimal_poker/templates/index.html
game_theory_optimal_poker/templates/auth/login.html
game_theory_optimal_poker/templates/auth/register.html
game_theory_optimal_poker-0.0.1.data/data/var/game_theory_optimal_poker-instance/schema.sql
game_theory_optimal_poker-0.0.1.dist-info/LICENSE
game_theory_optimal_poker-0.0.1.dist-info/METADATA
game_theory_optimal_poker-0.0.1.dist-info/WHEEL
game_theory_optimal_poker-0.0.1.dist-info/entry_points.txt
game_theory_optimal_poker-0.0.1.dist-info/top_level.txt
game_theory_optimal_poker-0.0.1.dist-info/RECORD
